<?xml version="1.0" encoding="utf-8" standalone="yes" ?>
<T3locallang>
    <meta type="array">
        <description>Context Sensitive Help (CSH) for table tx_formulaenergy_domain_model_formulas</description>
        <type>CSH</type>
        <csh_table>tx_formulaenergy_domain_model_formulas</csh_table>
    </meta>
    <data type="array">
        <languageKey index="default" type="array">
			<label index="energyformula.description">The formula wich is insert by user</label>
			<label index="gender.description">Ther gender from the person</label>
			<label index="firstname.description">Firstname from the person</label>
			<label index="lastname.description">Lastname from the person</label>
			<label index="companyname.description">Companyname</label>
			<label index="streetnumber.description">The name of the street and house number</label>
			<label index="zipcity.description">The name of the city and zip number</label>
			<label index="email.description">The user´s email</label>
			<label index="agbchecked.description">User has checked the agb</label>
			<label index="hide.description">is the data hidden</label>
			<label index="cookie.description">i like cookies</label>
			<label index="ipnumber.description">The ip number</label>
			<label index="votes.description">All votes given in month of publishing</label>
			<label index="finalvotes.description">Final votes, who will win</label>
		</languageKey>
    </data>
</T3locallang>